nnanno/__init__.py
nnanno/_nbdev.py
nnanno/annotate.py
nnanno/core.py
nnanno/inference.py
nnanno/sample.py
nnanno/data/all_year_counts.csv
nnanno-0.0.3.dist-info/LICENSE
nnanno-0.0.3.dist-info/METADATA
nnanno-0.0.3.dist-info/WHEEL
nnanno-0.0.3.dist-info/entry_points.txt
nnanno-0.0.3.dist-info/top_level.txt
nnanno-0.0.3.dist-info/RECORD
