Metadata-Version: 2.1
Name: nnanno
Version: 0.0.3
Summary: Sample and annotate Newspaper Navigator data for computer vision tasks
Home-page: https://github.com/Living-with-machines/nnanno/tree/main/
Author: Daniel van Strien
Author-email: daniel.van-strien@bl.uk
License: MIT License
Keywords: computer-vision,digital-humanities
Platform: UNKNOWN
Classifier: Development Status :: 5 - Production/Stable
Classifier: Intended Audience :: Developers
Classifier: Natural Language :: English
Classifier: Programming Language :: Python :: 3.6
Classifier: Programming Language :: Python :: 3.7
Classifier: Programming Language :: Python :: 3.8
Classifier: License :: OSI Approved :: MIT License
Requires-Python: >=3.6
License-File: LICENSE
Requires-Dist: pandas
Requires-Dist: tqdm
Requires-Dist: Pillow
Requires-Dist: cytoolz
Requires-Dist: ijson
Requires-Dist: requests-cache (>=0.6.0)
Requires-Dist: ipywidgets
Requires-Dist: simplejson
Requires-Dist: fastcore
